bgbb/__init__.py
bgbb/_version.py
bgbb/bgbb_likelihood.py
bgbb/bgbb_utils.py
bgbb/core.py
bgbb/numba_special.py
bgbb/wrappers.py
bgbb/sql/__init__.py
bgbb/sql/bgbb_udfs.py
bgbb/sql/sql_utils.py
bgbb-0.1.6.dist-info/METADATA
bgbb-0.1.6.dist-info/RECORD
bgbb-0.1.6.dist-info/WHEEL
bgbb-0.1.6.dist-info/top_level.txt
tests/__init__.py
tests/boot_utes.py
tests/conftest.py
tests/test_bgbb.py
tests/test_bgbb_likelihood.py
tests/test_bgbb_udfs.py
tests/test_numba_special.py
tests/test_rfn_query.py
tests/test_sql_utils.py
