Metadata-Version: 2.1
Name: bgbb
Version: 0.1.6
Summary: UNKNOWN
Home-page: UNKNOWN
License: ['Apache 2.0', 'MIT']
Platform: UNKNOWN
Classifier: Programming Language :: Python :: 3.5
Provides-Extra: test
Requires-Dist: lifetimes (==0.9)
Requires-Dist: numba (<=0.38,>=0.34)
Requires-Dist: scipy
Requires-Dist: pandas
Requires-Dist: numpy
Requires-Dist: pyarrow
Requires-Dist: pyspark
Provides-Extra: test
Requires-Dist: pytest; extra == 'test'
